mitto_sdk/__init__.py
mitto_sdk/client.py
mitto_sdk/__pycache__/__init__.cpython-36.pyc
mitto_sdk/__pycache__/client.cpython-36.pyc
python_mitto_sdk-0.0.7.dist-info/LICENSE
python_mitto_sdk-0.0.7.dist-info/METADATA
python_mitto_sdk-0.0.7.dist-info/WHEEL
python_mitto_sdk-0.0.7.dist-info/top_level.txt
python_mitto_sdk-0.0.7.dist-info/RECORD
