Metadata-Version: 2.1
Name: python-mitto-sdk
Version: 0.0.7
Summary: Python library to interact with Mitto's API.
Home-page: https://github.com/jfreels/python-mitto-sdk
Author: Justin Freels
Author-email: justin@zuar.com
License: UNKNOWN
Platform: UNKNOWN
Classifier: Programming Language :: Python :: 3
Classifier: License :: OSI Approved :: MIT License
Classifier: Operating System :: OS Independent
Requires-Python: >=3.6
Requires-Dist: requests
Provides-Extra: dev
Requires-Dist: setuptools ; extra == 'dev'
Requires-Dist: twine ; extra == 'dev'
Requires-Dist: wheel ; extra == 'dev'
Requires-Dist: python-dotenv ; extra == 'dev'
